{"data":{"allWordpressPost":{"edges":[{"node":{"id":"a03457fc-92d0-5357-a350-fbd262a5bd5c","title":"I&#8217;m Stoked About WASM and You Should Be Too","path":"/blog/im-stoked-about-wasm/","date":"2019-03-23T18:00:23.000Z","author":{"name":"Justin Jordan"},"yoast":{"metadesc":"WebAssembly (WASM) is one of the most exciting advancements in web technology since perhaps HTML5. It's about to make the internet faster and could completely blur the line between web and native. If it scares you, it shouldn't. WebAssembly is amazing!"},"featured_media":{"localFile":{"childImageSharp":{"original":{"src":"/static/wasm-square-60448dd6e618d57e443d704332d0adf7.png"}}}}}}]}}}